lmx/__init__.py
lmx/__main__.py
lmx/linearization/Delinearizer.py
lmx/linearization/Linearizer.py
lmx/linearization/LmxFile.py
lmx/linearization/__init__.py
lmx/linearization/vocabulary.py
lmx/symbolic/MxlFile.py
lmx/symbolic/PitchAlternator.py
lmx/symbolic/Pruner.py
lmx/symbolic/__init__.py
lmx/symbolic/actual_durations_to_fractional.py
lmx/symbolic/debug_compare.py
lmx/symbolic/fractional_durations_to_actual.py
lmx/symbolic/get_head_attributes.py
lmx/symbolic/part_to_score.py
lmx/symbolic/sort_attributes.py
lmx/symbolic/split_part_to_systems.py
linearized_musicxml-1.0.0.dist-info/METADATA
linearized_musicxml-1.0.0.dist-info/WHEEL
linearized_musicxml-1.0.0.dist-info/licenses/LICENSE
linearized_musicxml-1.0.0.dist-info/RECORD
