Metadata-Version: 2.3
Name: linearized-musicxml
Version: 1.0.0
Summary: MusicXML linearization for img2seq model training
Project-URL: Homepage, https://github.com/Jirka-Mayer/lmx
Project-URL: Issues, https://github.com/Jirka-Mayer/lmx/issues
Author-email: Jiří Mayer <mayer@ufal.mff.cuni.cz>
License-File: LICENSE
Classifier: Intended Audience :: Science/Research
Classifier: License :: OSI Approved :: MIT License
Classifier: Natural Language :: English
Classifier: Operating System :: OS Independent
Classifier: Programming Language :: Python :: 3
Requires-Python: >=3.8
